djangoldp_energiepartagee/__init__.py
djangoldp_energiepartagee/admin.py
djangoldp_energiepartagee/apps.py
djangoldp_energiepartagee/context_processors.py
djangoldp_energiepartagee/djangoldp_settings.py
djangoldp_energiepartagee/djangoldp_urls.py
djangoldp_energiepartagee/oidc_settings.py
djangoldp_energiepartagee/settings.py
djangoldp_energiepartagee/tests.py
djangoldp_energiepartagee/auth/__init__.py
djangoldp_energiepartagee/auth/backends.py
djangoldp_energiepartagee/filters/__init__.py
djangoldp_energiepartagee/filters/contribution_filter_backend.py
djangoldp_energiepartagee/filters/related_actor_filter_backend.py
djangoldp_energiepartagee/filters/updated_since_filter_backend.py
djangoldp_energiepartagee/migrations/0001_initial.py
djangoldp_energiepartagee/migrations/0002_auto_20210114_1101.py
djangoldp_energiepartagee/migrations/0003_profile_user.py
djangoldp_energiepartagee/migrations/0004_auto_20210114_1652.py
djangoldp_energiepartagee/migrations/0005_auto_20210118_1407.py
djangoldp_energiepartagee/migrations/0006_auto_20210119_1237.py
djangoldp_energiepartagee/migrations/0007_auto_20210120_1213.py
djangoldp_energiepartagee/migrations/0008_auto_20210120_1215.py
djangoldp_energiepartagee/migrations/0009_auto_20210120_1439.py
djangoldp_energiepartagee/migrations/0009_auto_20210120_1911.py
djangoldp_energiepartagee/migrations/0010_auto_20210120_1442.py
djangoldp_energiepartagee/migrations/0011_auto_20210120_1450.py
djangoldp_energiepartagee/migrations/0012_auto_20210120_1553.py
djangoldp_energiepartagee/migrations/0013_merge_20210120_1916.py
djangoldp_energiepartagee/migrations/0014_auto_20210121_1750.py
djangoldp_energiepartagee/migrations/0015_auto_20210122_1044.py
djangoldp_energiepartagee/migrations/0016_auto_20210122_1146.py
djangoldp_energiepartagee/migrations/0017_actor_iban.py
djangoldp_energiepartagee/migrations/0018_auto_20210122_1229.py
djangoldp_energiepartagee/migrations/0019_auto_20210124_1728.py
djangoldp_energiepartagee-3.0.2.dist-info/METADATA
djangoldp_energiepartagee-3.0.2.dist-info/WHEEL
djangoldp_energiepartagee-3.0.2.dist-info/top_level.txt
djangoldp_energiepartagee-3.0.2.dist-info/RECORD
