Metadata-Version: 2.1
Name: djangoldp-energiepartagee
Version: 3.0.2
Summary: Custom DjangoLDP based package for Energie Partagee
Home-page: UNKNOWN
License: MIT
Platform: UNKNOWN
Classifier: Programming Language :: Python :: 3
Requires-Dist: djangoldp (~=3.1)
Requires-Dist: reportlab (==3.6.13)
Requires-Dist: xhtml2pdf (~=0.2)
